odoo/addons/connector_prestashop/README.rst
odoo/addons/connector_prestashop/__init__.py
odoo/addons/connector_prestashop/__manifest__.py
odoo/addons/connector_prestashop/connector.py
odoo/addons/connector_prestashop/components/__init__.py
odoo/addons/connector_prestashop/components/auto_matching_importer.py
odoo/addons/connector_prestashop/components/backend_adapter.py
odoo/addons/connector_prestashop/components/binder.py
odoo/addons/connector_prestashop/components/core.py
odoo/addons/connector_prestashop/components/deleter.py
odoo/addons/connector_prestashop/components/exception.py
odoo/addons/connector_prestashop/components/exporter.py
odoo/addons/connector_prestashop/components/importer.py
odoo/addons/connector_prestashop/components/listener.py
odoo/addons/connector_prestashop/components/mapper.py
odoo/addons/connector_prestashop/components/version_key.py
odoo/addons/connector_prestashop/data/cron.xml
odoo/addons/connector_prestashop/data/ecommerce_data.xml
odoo/addons/connector_prestashop/data/product_decimal_precision.xml
odoo/addons/connector_prestashop/data/queue_job_data.xml
odoo/addons/connector_prestashop/demo/backend.xml
odoo/addons/connector_prestashop/i18n/connector_prestashop.pot
odoo/addons/connector_prestashop/i18n/es.po
odoo/addons/connector_prestashop/i18n/fr.po
odoo/addons/connector_prestashop/models/__init__.py
odoo/addons/connector_prestashop/models/account_move/__init__.py
odoo/addons/connector_prestashop/models/account_move/common.py
odoo/addons/connector_prestashop/models/account_move/importer.py
odoo/addons/connector_prestashop/models/account_payment_mode/__init__.py
odoo/addons/connector_prestashop/models/account_payment_mode/common.py
odoo/addons/connector_prestashop/models/account_payment_mode/importer.py
odoo/addons/connector_prestashop/models/account_tax/__init__.py
odoo/addons/connector_prestashop/models/account_tax/common.py
odoo/addons/connector_prestashop/models/account_tax/importer.py
odoo14_addon_connector_prestashop-14.0.2.0.2.dist-info/METADATA
odoo14_addon_connector_prestashop-14.0.2.0.2.dist-info/WHEEL
odoo14_addon_connector_prestashop-14.0.2.0.2.dist-info/top_level.txt
odoo14_addon_connector_prestashop-14.0.2.0.2.dist-info/RECORD
