Metadata-Version: 2.1
Name: odoo14-addon-connector-prestashop
Version: 14.0.2.0.2
Summary: PrestaShop-Odoo connector
Home-page: https://github.com/OCA/connector-prestashop
Author: Akretion,Camptocamp,AvanzOSC,Tecnativa,Mind And Go,Odoo Community Association (OCA)
Author-email: support@odoo-community.org
License: AGPL-3
Platform: UNKNOWN
Classifier: Programming Language :: Python
Classifier: Framework :: Odoo
Classifier: Framework :: Odoo :: 14.0
Classifier: License :: OSI Approved :: GNU Affero General Public License v3
Requires-Python: >=3.6
Requires-Dist: bs4
Requires-Dist: freezegun
Requires-Dist: html2text
Requires-Dist: odoo14-addon-connector-ecommerce
Requires-Dist: odoo14-addon-onchange-helper
Requires-Dist: odoo14-addon-product-multi-category
Requires-Dist: odoo14-addon-product-multi-image
Requires-Dist: odoo (<14.1dev,>=14.0a)
Requires-Dist: prestapyt
Requires-Dist: vcrpy
